vb3/Vera.ttf
vb3/__init__.py
vb3/battery.py
vb3/display.py
vb3/gpio.py
vb3/network.py
vb3/pixChicago.ttf
vb3/util.py
vb3/volumio.ppm
vb3/volumio_client.py
volumio_buddy-3.0.6.data/scripts/vbuddy
volumio_buddy-3.0.6.dist-info/LICENSE
volumio_buddy-3.0.6.dist-info/METADATA
volumio_buddy-3.0.6.dist-info/WHEEL
volumio_buddy-3.0.6.dist-info/top_level.txt
volumio_buddy-3.0.6.dist-info/RECORD
