Metadata-Version: 2.1
Name: volumio-buddy
Version: 3.0.6
Summary: Hardware add-ons integration for Volumio 3
Home-page: https://github.com/foxey/volumio-buddy
Author: Michiel Fokke
Author-email: michiel@fokke.org
Project-URL: Bug Tracker, https://github.com/foxey/volumio-buddy/issues
Keywords: Volumio,Volumio3,GPIO,SSD1306,OLED,Rotary Encoder,SocketIO
Classifier: Programming Language :: Python :: 3
Classifier: License :: OSI Approved :: GNU General Public License v3 (GPLv3)
Classifier: Operating System :: POSIX :: Linux
Classifier: Topic :: Multimedia :: Sound/Audio
Classifier: Topic :: System :: Hardware
Requires-Python: >=3.6
License-File: LICENSE
Requires-Dist: adafruit-circuitpython-ssd1306
Requires-Dist: adafruit-circuitpython-ina219
Requires-Dist: RPi.GPIO
Requires-Dist: python-socketio[asyncio_client] <5,>=4
Requires-Dist: pillow
